mwalas_skk_hello/__init__.py
mwalas_skk_hello/create_service.py
mwalas_skk_hello/hello.py
mwalas_skk_hello/mwalas-skk-hello.service
mwalas_skk_hello-4.0.1.data/scripts/create_service.py
mwalas_skk_hello-4.0.1.dist-info/METADATA
mwalas_skk_hello-4.0.1.dist-info/WHEEL
mwalas_skk_hello-4.0.1.dist-info/entry_points.txt
mwalas_skk_hello-4.0.1.dist-info/top_level.txt
mwalas_skk_hello-4.0.1.dist-info/RECORD
