Metadata-Version: 2.1
Name: mwalas-skk-hello
Version: 4.0.1
Summary: Hello world package test
Home-page: https://github.com/m-walas
Author: Mateusz Walas
Author-email: mateusz.walas@skk-logisticsdata.com
License: MIT
Keywords: hello,world,first,package
Classifier: Development Status :: 3 - Alpha
Classifier: Intended Audience :: Developers
Classifier: License :: OSI Approved :: MIT License
Classifier: Programming Language :: Python :: 3
Classifier: Programming Language :: Python :: 3.7
Classifier: Programming Language :: Python :: 3.8
Classifier: Programming Language :: Python :: 3.9
Classifier: Programming Language :: Python :: 3.10
Classifier: Programming Language :: Python :: 3.11
Requires-Dist: Pygments ==2.18.0
Requires-Dist: SecretStorage ==3.3.3
Requires-Dist: certifi ==2024.7.4
Requires-Dist: cffi ==1.16.0
Requires-Dist: charset-normalizer ==3.3.2
Requires-Dist: cryptography ==43.0.0
Requires-Dist: docutils ==0.21.2
Requires-Dist: idna ==3.7
Requires-Dist: importlib-metadata ==8.2.0
Requires-Dist: jaraco.classes ==3.4.0
Requires-Dist: jaraco.context ==5.3.0
Requires-Dist: jaraco.functools ==4.0.1
Requires-Dist: jeepney ==0.8.0
Requires-Dist: keyring ==25.2.1
Requires-Dist: markdown-it-py ==3.0.0
Requires-Dist: mdurl ==0.1.2
Requires-Dist: more-itertools ==10.3.0
Requires-Dist: nh3 ==0.2.18
Requires-Dist: pathlib
Requires-Dist: pkginfo ==1.10.0
Requires-Dist: pycparser ==2.22
Requires-Dist: readme-renderer ==44.0
Requires-Dist: requests-toolbelt ==1.0.0
Requires-Dist: requests ==2.32.3
Requires-Dist: rfc3986 ==2.0.0
Requires-Dist: rich ==13.7.1
Requires-Dist: setuptools ==67.7.2
Requires-Dist: twine ==5.1.1
Requires-Dist: urllib3 ==2.2.2
Requires-Dist: wheel ==0.43.0
Requires-Dist: zipp ==3.19.2
